{
  "cookies": [
    {
      "name": "locale",
      "value": "en",
      "domain": "www.sportybet.com",
      "path": "/",
      "expires": -1,
      "httpOnly": false,
      "secure": false,
      "sameSite": "None"
    },
    {
      "name": "sb_fs_id",
      "value": "f4b73eab-b377-4856-9353-1ad098b5c3b5",
      "domain": "www.sportybet.com",
      "path": "/",
      "expires": 1788460300,
      "httpOnly": false,
      "secure": false,
      "sameSite": "None"
    },
    {
      "name": "sb_fs_flag",
      "value": "false",
      "domain": "www.sportybet.com",
      "path": "/",
      "expires": 1788460300,
      "httpOnly": false,
      "secure": false,
      "sameSite": "None"
    },
    {
      "name": "device-id",
      "value": "86de9715-0382-4eaa-bb5a-df4444b8a00b",
      "domain": "www.sportybet.com",
      "path": "/",
      "expires": 1791484300,
      "httpOnly": false,
      "secure": false,
      "sameSite": "None"
    },
    {
      "name": "sb_country",
      "value": "ng",
      "domain": "www.sportybet.com",
      "path": "/",
      "expires": 1788460300,
      "httpOnly": false,
      "secure": false,
      "sameSite": "None"
    },
    {
      "name": "_gcl_au",
      "value": "1.1.842100731.1756924301",
      "domain": ".sportybet.com",
      "path": "/",
      "expires": 1764700301,
      "httpOnly": false,
      "secure": false,
      "sameSite": "None"
    },
    {
      "name": "_ga",
      "value": "GA1.1.1875542365.1756924301",
      "domain": ".sportybet.com",
      "path": "/",
      "expires": 1791484301,
      "httpOnly": false,
      "secure": false,
      "sameSite": "None"
    },
    {
      "name": "usrId",
      "value": "250903183141pdid69267092",
      "domain": "www.sportybet.com",
      "path": "/",
      "expires": -1,
      "httpOnly": false,
      "secure": false,
      "sameSite": "None"
    },
    {
      "name": "_ga_D9PX9RRZRJ",
      "value": "GS2.1.s1756924301$o1$g0$t1756924303$j58$l0$h0",
      "domain": ".sportybet.com",
      "path": "/",
      "expires": 1791484303,
      "httpOnly": false,
      "secure": false,
      "sameSite": "None"
    },
    {
      "name": "accessToken",
      "value": "patron:id:accesstoken:6baa3b4d1361b21a0f06fd2fc0d37343H8RS1ls3NndVTp5bKS4ZtCssNHQbDpDZXY3OWKMA251Su9unqI6A799jkVKFAWZeIc+uPLUYcWmmJeO+eCWpcQ==",
      "domain": "www.sportybet.com",
      "path": "/",
      "expires": -1,
      "httpOnly": false,
      "secure": false,
      "sameSite": "None"
    },
    {
      "name": "refreshToken",
      "value": "patron:id:refreshtoken:3f589c5d23c14d20841388573244058d",
      "domain": "www.sportybet.com",
      "path": "/",
      "expires": 1759516304,
      "httpOnly": false,
      "secure": false,
      "sameSite": "None"
    },
    {
      "name": "deviceId",
      "value": "250903183141bdid69267090",
      "domain": "www.sportybet.com",
      "path": "/",
      "expires": 1759516304,
      "httpOnly": false,
      "secure": false,
      "sameSite": "None"
    },
    {
      "name": "userId",
      "value": "G240608065027puid07872939",
      "domain": "www.sportybet.com",
      "path": "/",
      "expires": 1759516304,
      "httpOnly": false,
      "secure": false,
      "sameSite": "None"
    },
    {
      "name": "selfExclusionType",
      "value": "",
      "domain": "www.sportybet.com",
      "path": "/",
      "expires": 1764700304,
      "httpOnly": false,
      "secure": true,
      "sameSite": "None"
    },
    {
      "name": "selfExclusionStartDate",
      "value": "0",
      "domain": "www.sportybet.com",
      "path": "/",
      "expires": 1764700304,
      "httpOnly": false,
      "secure": true,
      "sameSite": "None"
    },
    {
      "name": "selfExclusionEndDate",
      "value": "0",
      "domain": "www.sportybet.com",
      "path": "/",
      "expires": 1764700304,
      "httpOnly": false,
      "secure": true,
      "sameSite": "None"
    },
    {
      "name": "selfExclusionCooldown",
      "value": "false",
      "domain": "www.sportybet.com",
      "path": "/",
      "expires": 1764700304,
      "httpOnly": false,
      "secure": true,
      "sameSite": "None"
    },
    {
      "name": "_ga_00HZ52K43N",
      "value": "GS2.1.s1756924301$o1$g0$t1756924304$j57$l0$h0",
      "domain": ".sportybet.com",
      "path": "/",
      "expires": 1791484304,
      "httpOnly": false,
      "secure": false,
      "sameSite": "None"
    },
    {
      "name": "phone",
      "value": "9120183273",
      "domain": "www.sportybet.com",
      "path": "/",
      "expires": 1788460304,
      "httpOnly": false,
      "secure": false,
      "sameSite": "None"
    },
    {
      "name": "lastUserId",
      "value": "G240608065027puid07872939",
      "domain": "www.sportybet.com",
      "path": "/",
      "expires": 1759602704,
      "httpOnly": false,
      "secure": false,
      "sameSite": "None"
    },
    {
      "name": "user_segment",
      "value": "D1",
      "domain": "www.sportybet.com",
      "path": "/",
      "expires": 1757010704,
      "httpOnly": false,
      "secure": false,
      "sameSite": "None"
    },
    {
      "name": "userCert",
      "value": "350",
      "domain": "www.sportybet.com",
      "path": "/",
      "expires": -1,
      "httpOnly": false,
      "secure": false,
      "sameSite": "None"
    }
  ],
  "origins": [
    {
      "origin": "https://www.sportybet.com",
      "localStorage": [
        {
          "name": "acceptChanges_G240608065027puid07872939",
          "value": "0"
        },
        {
          "name": "login_without_click_download_banner_count",
          "value": "1"
        },
        {
          "name": "notification_unread",
          "value": "1756924304930"
        },
        {
          "name": "_gcl_ls",
          "value": "{\"schema\":\"gcl\",\"version\":1,\"gcl_ctr\":{\"value\":{\"value\":0,\"timeouts\":0,\"creationTimeMs\":1756924300657},\"expires\":1764700300657}}"
        },
        {
          "name": "notification_request_permission_time",
          "value": "1756924304784"
        },
        {
          "name": "last_time_sub_promo_msg",
          "value": "1756924304878"
        },
        {
          "name": "hasSimulateGameNewResult",
          "value": "{\"G240608065027puid07872939\":false}"
        },
        {
          "name": "retainSelectionsAfterRebet_G240608065027puid07872939",
          "value": "0"
        },
        {
          "name": "remember_me",
          "value": "1"
        },
        {
          "name": "daily_reward_last_subscribe",
          "value": "1756924304878"
        },
        {
          "name": "removeSuspended_G240608065027puid07872939",
          "value": "0"
        },
        {
          "name": "com.grafana.faro.session",
          "value": "{\"sessionId\":\"7BogE8DJs9\",\"lastActivity\":1756924305086,\"started\":1756924302079,\"isSampled\":true,\"sessionMeta\":{\"id\":\"7BogE8DJs9\",\"attributes\":{\"isSampled\":\"true\"}}}"
        },
        {
          "name": "h5_odds_boost",
          "value": "{\"pId\":\"200521133502odbp32275254\",\"status\":false}"
        },
        {
          "name": "keep_signed_in",
          "value": "1"
        },
        {
          "name": "user_odds_format",
          "value": "DECIMAL"
        }
      ]
    },
    {
      "origin": "https://www.google.com",
      "localStorage": [
        {
          "name": "rc::a",
          "value": "MW54ODJsbjF3cTc0ZHM="
        }
      ]
    }
  ]
}